pydeplist/__init__.py
pydeplist/pydeplist.py
pydeplist/cli/__init__.py
pydeplist/cli/cli.py
pydeplist/utils/__init__.py
pydeplist/utils/setup_load.py
pydeplist-0.0.1.dist-info/METADATA
pydeplist-0.0.1.dist-info/WHEEL
pydeplist-0.0.1.dist-info/entry_points.txt
pydeplist-0.0.1.dist-info/top_level.txt
pydeplist-0.0.1.dist-info/RECORD
