Metadata-Version: 2.1
Name: pydeplist
Version: 0.0.1
Summary: A tool to list tree of all the python dependencies which are in GitHub.
Home-page: https://github.com/yuukidach/pydeplist
Author: yuukidach
Author-email: chendamailbox@foxmail.com
License: UNKNOWN
Platform: UNKNOWN
Requires-Dist: Click (==7.0)
